LICENSE
README.md
pyproject.toml
requirements.txt
sibilant/__init__.py
sibilant/_package_metadata.py
sibilant/constants.py
sibilant/exceptions.py
sibilant/helpers.py
sibilant/py.typed
sibilant/structures.py
sibilant.egg-info/PKG-INFO
sibilant.egg-info/SOURCES.txt
sibilant.egg-info/dependency_links.txt
sibilant.egg-info/requires.txt
sibilant.egg-info/top_level.txt
sibilant/codecs/__init__.py
sibilant/codecs/base.py
sibilant/codecs/g711.py
sibilant/rtp/__init__.py
sibilant/rtp/client.py
sibilant/rtp/dtmf.py
sibilant/rtp/packet.py
sibilant/sdp/__init__.py
sibilant/sdp/common.py
sibilant/sdp/media.py
sibilant/sdp/session.py
sibilant/sdp/time.py
sibilant/sip/__init__.py
sibilant/sip/client.py
sibilant/sip/headers.py
sibilant/sip/messages.py
sibilant/voip/__init__.py
sibilant/voip/phone.py
tests/test_rtp.py
tests/test_sip.py
tests/test_voip.py