Metadata-Version: 2.2
Name: sibilant
Version: 0.3.4
Summary: sibilant makes python communicate over VoIP
Author-email: abk16 <awaken.mulled505@4wrd.cc>
License: MPL-2.0
Project-URL: Homepage, https://github.com/andreabak/sibilant
Requires-Python: >=3.8
License-File: LICENSE
Requires-Dist: cbitstruct
Requires-Dist: frozendict
Requires-Dist: numpy
Requires-Dist: toml
Requires-Dist: typing-extensions
